{
  "hash": "5db738b05d9148128a240b0e2c1cb935c2805192bf98a579421aacda364c8dae",
  "size_bytes": 9894,
  "export_count": 16,
  "import_count": 20,
  "exports": [
    "_",
    "__data_end",
    "__heap_base",
    "all_pairs",
    "all_pairs_length",
    "create_pair",
    "fee_to",
    "fee_to_setter",
    "fees_enabled",
    "get_pair",
    "initialize",
    "memory",
    "pair_exists",
    "set_fee_to",
    "set_fee_to_setter",
    "set_fees_enabled"
  ],
  "imports": [
    "a.0",
    "b.4",
    "b.8",
    "b._",
    "b.e",
    "b.i",
    "b.j",
    "c._",
    "d._",
    "l.0",
    "l.1",
    "l.3",
    "l.7",
    "l.8",
    "l._",
    "m.9",
    "v.g",
    "x.0",
    "x.1",
    "x.7"
  ],
  "all_strings_count": 65,
  "topic_like_strings": [
    "all_pairs",
    "all_pairs_length",
    "asm",
    "contractenvmetav0",
    "contractmetav0",
    "contractspecv0",
    "create_pair",
    "fee_to",
    "fee_to_setter",
    "fees_enabled",
    "get_pair",
    "initialize",
    "is_enabled",
    "memory",
    "new",
    "new_pairs_length",
    "new_setter",
    "newold",
    "old",
    "pair",
    "pair_exists",
    "pair_wasm_hash",
    "rssdkver",
    "rsver",
    "set_fee_to",
    "set_fee_to_setter",
    "set_fees_enabled",
    "setter",
    "token_0",
    "token_1",
    "token_a",
    "token_b"
  ]
}