{
  "hash": "a67ad7715ecb3e174a1afe731d9f534e616dac3d5b115781762ec531c2ce1d30",
  "size_bytes": 34441,
  "export_count": 55,
  "import_count": 55,
  "exports": [
    "_",
    "__data_end",
    "__heap_base",
    "claim",
    "config_global_rewards",
    "config_pool_rewards",
    "configure_init_pool_payment",
    "deposit",
    "distribute_outstanding_reward",
    "estimate_swap",
    "fill_liquidity",
    "get_info",
    "get_init_pool_payment_address",
    "get_init_pool_payment_token",
    "get_liquidity",
    "get_liquidity_calculator",
    "get_operator",
    "get_plane",
    "get_pool",
    "get_pools",
    "get_pools_for_tokens_range",
    "get_reserves",
    "get_rewards_config",
    "get_rewards_info",
    "get_stable_pool_payment_amount",
    "get_standard_pool_payment_amount",
    "get_tokens",
    "get_tokens_for_reward",
    "get_tokens_sets_count",
    "get_total_accumulated_reward",
    "get_total_claimed_reward",
    "get_total_configured_reward",
    "get_total_liquidity",
    "get_total_outstanding_reward",
    "get_total_shares",
    "get_user_reward",
    "init_admin",
    "init_stableswap_pool",
    "init_standard_pool",
    "memory",
    "pool_type",
    "remove_pool",
    "set_liquidity_calculator",
    "set_operator",
    "set_pool_hash",
    "set_pools_plane",
    "set_reward_token",
    "set_stableswap_pool_hash",
    "set_token_hash",
    "share_id",
    "swap",
    "swap_chained",
    "upgrade",
    "version",
    "withdraw"
  ],
  "imports": [
    "a.0",
    "a.3",
    "b.3",
    "b.4",
    "b.8",
    "b._",
    "b.b",
    "b.e",
    "b.f",
    "b.j",
    "c._",
    "d._",
    "i.0",
    "i.3",
    "i.4",
    "i.5",
    "i.6",
    "i.7",
    "i.8",
    "i._",
    "i.a",
    "i.b",
    "i.n",
    "i.p",
    "i.q",
    "l.0",
    "l.1",
    "l.3",
    "l.6",
    "l.7",
    "l.8",
    "l._",
    "m.0",
    "m.1",
    "m.2",
    "m.3",
    "m.4",
    "m.5",
    "m.6",
    "m.9",
    "m._",
    "m.a",
    "v.1",
    "v.3",
    "v.6",
    "v._",
    "v.d",
    "v.g",
    "v.h",
    "x.0",
    "x.1",
    "x.3",
    "x.5",
    "x.7",
    "x.8"
  ],
  "all_strings_count": 191,
  "topic_like_strings": [
    "account",
    "accumulated",
    "address",
    "admin",
    "argscontractfn_name",
    "asm",
    "block",
    "calculator",
    "claim",
    "claimed",
    "config_global_rewards",
    "config_pool_rewards",
    "configure_init_pool_payment",
    "contextsub_invocations",
    "contractenvmetav0",
    "contractmetav0",
    "contractspecv0",
    "current_block",
    "current_blockexpired_attps",
    "deposit",
    "desired_amounts",
    "distribute_outstanding_reward",
    "end",
    "estimate_swap",
    "expired_at",
    "fee_fraction",
    "fill_liquidity",
    "from",
    "get_info",
    "get_init_pool_payment_address",
    "get_init_pool_payment_token",
    "get_liquidity",
    "get_liquidity_calculator",
    "get_operator",
    "get_plane",
    "get_pool",
    "get_pools",
    "get_pools_for_tokens_range",
    "get_reserves",
    "get_rewards_config",
    "get_rewards_info",
    "get_stable_pool_payment_amount",
    "get_tokens",
    "get_tokens_for_reward",
    "get_tokens_sets_count",
    "get_total_accumulated_reward",
    "get_total_claimed_reward",
    "get_total_configured_reward",
    "get_total_liquidity",
    "get_total_outstanding_reward",
    "get_total_shares",
    "get_user_reward",
    "in_amount",
    "index",
    "init_admin",
    "init_stableswap_pool",
    "init_standard_pool",
    "last_block",
    "last_time",
    "memory",
    "min_amounts",
    "min_shares",
    "new_hash",
    "new_wasm_hash",
    "operator",
    "out_min",
    "plane",
    "pool_accumulated",
    "pool_hash",
    "pool_index",
    "pool_type",
    "processed",
    "remove_pool",
    "reward_token",
    "reward_tps",
    "rssdkver",
    "rsver",
    "set_liquidity_calculator",
    "set_operator",
    "set_pool_hash",
    "set_pools_plane",
    "set_reward_token",
    "set_stableswap_pool_hash",
    "set_token_hash",
    "share_amount",
    "share_id",
    "stable_pool_amount",
    "standard_pool_amount",
    "start",
    "swap",
    "swap_chained",
    "swaps_chain",
    "to_claim",
    "token",
    "token_in",
    "token_out",
    "tokens",
    "tokens_votes",
    "total_liquidity",
    "tps",
    "transfer_from",
    "upgrade",
    "user",
    "version",
    "voting_share",
    "withdraw"
  ]
}